my_package_byteorium/__init__.py
my_package_byteorium/__main__.py
my_package_byteorium/my_module.py
my_package_byteorium/my_subpackage/__init__.py
my_package_byteorium/my_subpackage/my_submodule.py
my_package_byteorium-0.1.6.dist-info/METADATA
my_package_byteorium-0.1.6.dist-info/WHEEL
my_package_byteorium-0.1.6.dist-info/entry_points.txt
my_package_byteorium-0.1.6.dist-info/licenses/LICENSE
my_package_byteorium-0.1.6.dist-info/RECORD
