Metadata-Version: 2.4
Name: my_package_byteorium
Version: 0.1.6
Summary: Python project template for building robust, modern, and clean Python projects.
License: MIT
License-File: LICENSE
Keywords: template,example
Author: mab0189
Requires-Python: >=3.12
Classifier: Programming Language :: Python :: 3.12
Classifier: License :: OSI Approved :: MIT License
Classifier: Operating System :: OS Independent
Classifier: Development Status :: 3 - Alpha
Classifier: Intended Audience :: Developers
Project-URL: Repository, https://github.com/mab0189/python_project_template_byteorium
